pydisc/Bot.py
pydisc/__init__.py
pydisc/api.py
pydisc/ws.py
pydisc/setup/__init__.py
pydisc/setup/command.py
pydisc/types/__init__.py
pydisc/types/interaction.py
pydisc/types/message.py
pydisc/types/user.py
pydisc-0.1.1.dist-info/LICENSE
pydisc-0.1.1.dist-info/METADATA
pydisc-0.1.1.dist-info/WHEEL
pydisc-0.1.1.dist-info/top_level.txt
pydisc-0.1.1.dist-info/RECORD
