Metadata-Version: 2.1
Name: pydisc
Version: 0.1.1
Summary: a discord bot wrapper for python have slash command
Home-page: https://github.com/pydisc/pydisc
Author: cutebear0123
License: MIT
Platform: UNKNOWN
Classifier: Development Status :: 3 - Alpha
Classifier: Topic :: Internet
Classifier: Topic :: Software Development :: Libraries
Classifier: Topic :: Software Development :: Libraries :: Python Modules
Classifier: Topic :: Utilities
Classifier: Typing :: Typed
Classifier: Intended Audience :: Developers
Classifier: Programming Language :: Python :: 3
Classifier: License :: OSI Approved :: MIT License
Requires-Python: >=3.7
License-File: LICENSE
Requires-Dist: websockets
Requires-Dist: requests
